pipen_diagram/__init__.py
pipen_diagram/diagram.py
pipen_diagram/entry.py
pipen_diagram-1.1.0.dist-info/METADATA
pipen_diagram-1.1.0.dist-info/WHEEL
pipen_diagram-1.1.0.dist-info/entry_points.txt
pipen_diagram-1.1.0.dist-info/RECORD
